{
  "domaines": {
    "SenseursPassifs": {
      "module": "millegrilles.domaines.SenseursPassifs",
      "classe": "GestionnaireSenseursPassifs"
    },
    "Plume": {
      "module": "millegrilles.domaines.Plume",
      "classe": "GestionnairePlume"
    },
    "Messagerie": {
      "module": "millegrilles.domaines.Messagerie",
      "classe": "GestionnaireMessagerie"
    },
    "GrosFichiers": {
      "module": "millegrilles.domaines.GrosFichiers",
      "classe": "GestionnaireGrosFichiers"
    }
  }
}